MANIFEST.in
setup.py
Products/__init__.py
Products.SilvaMetadata.egg-info/PKG-INFO
Products.SilvaMetadata.egg-info/SOURCES.txt
Products.SilvaMetadata.egg-info/dependency_links.txt
Products.SilvaMetadata.egg-info/namespace_packages.txt
Products.SilvaMetadata.egg-info/not-zip-safe
Products.SilvaMetadata.egg-info/requires.txt
Products.SilvaMetadata.egg-info/top_level.txt
Products/SilvaMetadata/API.txt
Products/SilvaMetadata/Binding.py
Products/SilvaMetadata/CREDITS.txt
Products/SilvaMetadata/Collection.py
Products/SilvaMetadata/Element.py
Products/SilvaMetadata/Exceptions.py
Products/SilvaMetadata/Export.py
Products/SilvaMetadata/Expression.py
Products/SilvaMetadata/FormulatorField.py
Products/SilvaMetadata/Guard.py
Products/SilvaMetadata/HISTORY.txt
Products/SilvaMetadata/Import.py
Products/SilvaMetadata/Index.py
Products/SilvaMetadata/LICENSE.txt
Products/SilvaMetadata/MetadataTool.py
Products/SilvaMetadata/README.txt
Products/SilvaMetadata/Set.py
Products/SilvaMetadata/TypeMapping.py
Products/SilvaMetadata/XMLType.py
Products/SilvaMetadata/__init__.py
Products/SilvaMetadata/configure.zcml
Products/SilvaMetadata/interfaces.py
Products/SilvaMetadata/metadata.png
Products/SilvaMetadata/utils.py
Products/SilvaMetadata/MetadataTool_templates/metadatatooloverview.pt
Products/SilvaMetadata/MetadataTool_templates/metadatatypemapping.pt
Products/SilvaMetadata/tests/__init__.py
Products/SilvaMetadata/tests/test_import_export.py
Products/SilvaMetadata/tests/test_metadata.py
Products/SilvaMetadata/tests/data/dublin_core.xml
Products/SilvaMetadata/tests/data/sample_export.xml
Products/SilvaMetadata/ui/ElementAddForm.dtml
Products/SilvaMetadata/ui/ElementGuardForm.dtml
Products/SilvaMetadata/ui/ElementPolicyForm.dtml
Products/SilvaMetadata/ui/MetadataSetAddForm.dtml
Products/SilvaMetadata/ui/SetContainerView.dtml
Products/SilvaMetadata/ui/SetSettingsForm.dtml
Products/SilvaMetadata/www/bottom.gif
Products/SilvaMetadata/www/down.gif
Products/SilvaMetadata/www/top.gif
Products/SilvaMetadata/www/up.gif