Metadata-Version: 1.1
Name: Products.SilvaMetadata
Version: 3.0.1
Summary: Metadata support for Silva
Home-page: https://github.com/silvacms/Products.SilvaMetadata
Author: Infrae
Author-email: info@infrae.com
License: BSD
Keywords: silva zope2 metadata
Platform: UNKNOWN
Classifier: Framework :: Zope2
Classifier: License :: OSI Approved :: BSD License
Classifier: Programming Language :: Python
Classifier: Topic :: Software Development :: Libraries :: Python Modules
